<?xml version="1.0" encoding="utf-8" ?>
<dwsync>
<file name="bootstrap-theme.css" server="ec2-18-216-179-0.us-east-2.compute.amazonaws.com//var/www/html/" local="133564820187378266" remote="133564820540000000" Dst="2" />
<file name="bootstrap-theme.css.map" server="ec2-18-216-179-0.us-east-2.compute.amazonaws.com//var/www/html/" local="133564820187460976" remote="133564820540000000" Dst="2" />
<file name="bootstrap-theme.min.css" server="ec2-18-216-179-0.us-east-2.compute.amazonaws.com//var/www/html/" local="133564820187579834" remote="133564820540000000" Dst="2" />
<file name="bootstrap-theme.min.css.map" server="ec2-18-216-179-0.us-east-2.compute.amazonaws.com//var/www/html/" local="133564820187699924" remote="133564820550000000" Dst="2" />
<file name="bootstrap.css" server="ec2-18-216-179-0.us-east-2.compute.amazonaws.com//var/www/html/" local="133564820187739570" remote="133564820550000000" Dst="2" />
<file name="bootstrap.css.map" server="ec2-18-216-179-0.us-east-2.compute.amazonaws.com//var/www/html/" local="133564820187789543" remote="133564820560000000" Dst="2" />
<file name="bootstrap.min.css" server="ec2-18-216-179-0.us-east-2.compute.amazonaws.com//var/www/html/" local="133564820187819557" remote="133564820560000000" Dst="2" />
<file name="bootstrap.min.css.map" server="ec2-18-216-179-0.us-east-2.compute.amazonaws.com//var/www/html/" local="133564820187889549" remote="133564820570000000" Dst="2" />
<file name="font-awesome.min.css" server="ec2-18-216-179-0.us-east-2.compute.amazonaws.com//var/www/html/" local="133564820187919568" remote="133564820580000000" Dst="2" />
<file name="main.css" server="ec2-18-216-179-0.us-east-2.compute.amazonaws.com//var/www/html/" local="133564820187949564" remote="133564820580000000" Dst="2" />
<file name="owl.carousel.css" server="ec2-18-216-179-0.us-east-2.compute.amazonaws.com//var/www/html/" local="133564820187979571" remote="133564820580000000" Dst="2" />
<file name="owl.theme.default.min.css" server="ec2-18-216-179-0.us-east-2.compute.amazonaws.com//var/www/html/" local="133564820188009567" remote="133564820580000000" Dst="2" />
<file name="templatemo-style.css" server="ec2-18-216-179-0.us-east-2.compute.amazonaws.com//var/www/html/" local="133564820188049569" remote="133564820590000000" Dst="2" />
</dwsync>